estimators/__init__.py
estimators/basic-usage.py
estimators/math.py
estimators/bandits/__init__.py
estimators/bandits/base.py
estimators/bandits/cats_utils.py
estimators/bandits/clopper_pearson.py
estimators/bandits/cressieread.py
estimators/bandits/dr.py
estimators/bandits/gaussian.py
estimators/bandits/ips.py
estimators/bandits/mle.py
estimators/bandits/snips.py
estimators/ccb/__init__.py
estimators/ccb/base.py
estimators/ccb/first_slot.py
estimators/ccb/multislot.py
estimators/ccb/pdis_cressieread.py
estimators/slates/__init__.py
estimators/slates/base.py
estimators/slates/gaussian.py
estimators/slates/pseudo_inverse.py
estimators/utils/__init__.py
estimators/utils/ds_parse.py
vw_estimators-0.1.1.dist-info/LICENSE
vw_estimators-0.1.1.dist-info/METADATA
vw_estimators-0.1.1.dist-info/WHEEL
vw_estimators-0.1.1.dist-info/top_level.txt
vw_estimators-0.1.1.dist-info/RECORD
