Metadata-Version: 2.1
Name: vw-estimators
Version: 0.1.1
Summary: Python package of estimators to perform off-policy evaluation
Home-page: https://github.com/VowpalWabbit/estimators.git
License: BSD 3-Clause License
Platform: UNKNOWN
Classifier: Intended Audience :: Science/Research
Classifier: License :: OSI Approved :: BSD License
Classifier: Programming Language :: Python :: 3.6
Classifier: Operating System :: OS Independent
Classifier: Topic :: Scientific/Engineering
Requires-Python: >=3.6
License-File: LICENSE
Requires-Dist: scipy (>=0.9)
